consolecmdtools/__init__.py
consolecmdtools/__main__.py
consolecmdtools/path.py
consolecmdtools-6.6.3.dist-info/LICENSE
consolecmdtools-6.6.3.dist-info/METADATA
consolecmdtools-6.6.3.dist-info/WHEEL
consolecmdtools-6.6.3.dist-info/top_level.txt
consolecmdtools-6.6.3.dist-info/RECORD
