Metadata-Version: 2.2
Name: consolecmdtools
Version: 6.6.3
Summary: Console command tools in Python
Author-email: Kyan <kai@kyan001.com>
License: MIT License
Project-URL: Homepage, https://github.com/kyan001/PyConsoleCMDTools
Project-URL: Issue Tracker, https://github.com/kyan001/PyConsoleCMDTools/issues
Project-URL: Source Code, https://github.com/kyan001/PyConsoleCMDTools
Keywords: python,console,command,tool
Classifier: Development Status :: 5 - Production/Stable
Classifier: Intended Audience :: Developers
Classifier: Topic :: Software Development :: User Interfaces
Classifier: License :: OSI Approved :: MIT License
Classifier: Programming Language :: Python :: 3
Classifier: Programming Language :: Python :: 3 :: Only
Requires-Python: >=3.6
License-File: LICENSE
Requires-Dist: consoleiotools
Provides-Extra: opt
Requires-Dist: pillow; extra == "opt"
Provides-Extra: dev
Requires-Dist: build; extra == "dev"
Requires-Dist: twine; extra == "dev"
Requires-Dist: wheel; extra == "dev"
